infero/__init__.py
infero/convert/__init__.py
infero/convert/onnx.py
infero/main.py
infero/pull/__init__.py
infero/pull/download.py
infero/pull/models.py
infero/pull/supported_architectures.yaml
infero/serve/__init__.py
infero/serve/server.py
infero/utils.py
infero-0.0.16.dist-info/LICENSE
infero-0.0.16.dist-info/METADATA
infero-0.0.16.dist-info/WHEEL
infero-0.0.16.dist-info/entry_points.txt
infero-0.0.16.dist-info/RECORD
