Metadata-Version: 2.1
Name: infero
Version: 0.0.16
Summary: Easily download, convert, and host your models using the ONNX runtime
License: MIT
Author: ameen-91
Author-email: mohammedameen9011@gmail.com
Requires-Python: >=3.12,<4.0
Classifier: License :: OSI Approved :: MIT License
Classifier: Programming Language :: Python :: 3
Classifier: Programming Language :: Python :: 3.12
Classifier: Programming Language :: Python :: 3.13
Provides-Extra: gpu
Requires-Dist: fastapi[standard] (>=0.115.5,<0.116.0)
Requires-Dist: onnx (>=1.17.0,<2.0.0)
Requires-Dist: onnxruntime (>=1.20.1,<2.0.0)
Requires-Dist: psutil (>=6.1.0,<7.0.0)
Requires-Dist: pyyaml (>=6.0.2,<7.0.0)
Requires-Dist: requests (>=2.32.3,<3.0.0)
Requires-Dist: tabulate (>=0.9.0,<0.10.0)
Requires-Dist: torch (>=2.5.1,<3.0.0)
Requires-Dist: tqdm (>=4.67.0,<5.0.0)
Requires-Dist: transformers (>=4.46.3,<5.0.0)
Requires-Dist: typer[all] (>=0.13.1,<0.14.0)
